sleeperpy/__init__.py
sleeperpy/avatars.py
sleeperpy/drafts.py
sleeperpy/leagues.py
sleeperpy/players.py
sleeperpy/user.py
sleeper_py-1.0.1.dist-info/LICENSE
sleeper_py-1.0.1.dist-info/METADATA
sleeper_py-1.0.1.dist-info/WHEEL
sleeper_py-1.0.1.dist-info/top_level.txt
sleeper_py-1.0.1.dist-info/RECORD
