Metadata-Version: 2.1
Name: sleeper-py
Version: 1.0.1
Summary: A Python implementation of the Sleeper API.
Author-email: Adam Curtis <adamcurtisvt@gmail.com>
License: MIT License
Project-URL: Homepage, https://github.com/AdamCurtisVT/sleeper-py
Keywords: Sleeper,API,Fantasy Football
Classifier: License :: OSI Approved :: MIT License
Classifier: Programming Language :: Python
Classifier: Programming Language :: Python :: 3
Requires-Python: >=3.7
License-File: LICENSE
Requires-Dist: requests >=2.28.1
